inverters/__about__.py
inverters/__init__.py
inverters-0.0.5.dist-info/METADATA
inverters-0.0.5.dist-info/WHEEL
inverters-0.0.5.dist-info/licenses/LICENSE
inverters-0.0.5.dist-info/RECORD
