Metadata-Version: 2.3
Name: inverters
Version: 0.0.5
Project-URL: Documentation, https://github.com/Arty-Facts/inverters#readme
Project-URL: Issues, https://github.com/Arty-Facts/inverters/issues
Project-URL: Source, https://github.com/Arty-Facts/inverters
Author-email: Arturas Aleksandraus <arturas@aleksandraus.se>, Nithesh Chandher Karthikeyan <nithesh.chandher.karthikeyan@liu.se>
License-Expression: Apache-2.0
License-File: LICENSE
Classifier: Development Status :: 3 - Alpha
Classifier: Programming Language :: Python
Classifier: Programming Language :: Python :: 3.8
Classifier: Programming Language :: Python :: 3.9
Classifier: Programming Language :: Python :: 3.10
Classifier: Programming Language :: Python :: 3.11
Classifier: Programming Language :: Python :: 3.12
Classifier: Programming Language :: Python :: Implementation :: CPython
Classifier: Programming Language :: Python :: Implementation :: PyPy
Requires-Python: >=3.8
